odoo/addons/ssi_hr_recruitment/README.rst
odoo/addons/ssi_hr_recruitment/__init__.py
odoo/addons/ssi_hr_recruitment/__manifest__.py
odoo/addons/ssi_hr_recruitment/menu.xml
odoo/addons/ssi_hr_recruitment/data/automation/base_automation_data.xml
odoo/addons/ssi_hr_recruitment/data/automation/ir_actions_server_data.xml
odoo/addons/ssi_hr_recruitment/data/multiple_approval/recruitment_applicant_approval_template_data.xml
odoo/addons/ssi_hr_recruitment/data/multiple_approval/recruitment_vacancy_approval_template_data.xml
odoo/addons/ssi_hr_recruitment/data/policy/recruitment_applicant_policy_template_data.xml
odoo/addons/ssi_hr_recruitment/data/policy/recruitment_vacancy_policy_template_data.xml
odoo/addons/ssi_hr_recruitment/data/sequence/ir_sequence_data.xml
odoo/addons/ssi_hr_recruitment/data/sequence/recruitment_applicant_sequence_template_data.xml
odoo/addons/ssi_hr_recruitment/data/sequence/recruitment_vacancy_sequence_template_data.xml
odoo/addons/ssi_hr_recruitment/models/__init__.py
odoo/addons/ssi_hr_recruitment/models/recruitment_applicant.py
odoo/addons/ssi_hr_recruitment/models/recruitment_stage.py
odoo/addons/ssi_hr_recruitment/models/recruitment_stage_result.py
odoo/addons/ssi_hr_recruitment/models/recruitment_vacancy.py
odoo/addons/ssi_hr_recruitment/models/experience/__init__.py
odoo/addons/ssi_hr_recruitment/models/experience/applicant_academic.py
odoo/addons/ssi_hr_recruitment/models/experience/applicant_certification.py
odoo/addons/ssi_hr_recruitment/models/experience/applicant_experience.py
odoo/addons/ssi_hr_recruitment/models/experience/applicant_experience_mixin.py
odoo/addons/ssi_hr_recruitment/models/identification/__init__.py
odoo/addons/ssi_hr_recruitment/models/identification/applicant_id_number.py
odoo/addons/ssi_hr_recruitment/models/language/__init__.py
odoo/addons/ssi_hr_recruitment/models/language/applicant_languange.py
odoo/addons/ssi_hr_recruitment/security/ir.model.access.csv
odoo14_addon_ssi_hr_recruitment-14.0.1.0.1.dev1.dist-info/METADATA
odoo14_addon_ssi_hr_recruitment-14.0.1.0.1.dev1.dist-info/WHEEL
odoo14_addon_ssi_hr_recruitment-14.0.1.0.1.dev1.dist-info/top_level.txt
odoo14_addon_ssi_hr_recruitment-14.0.1.0.1.dev1.dist-info/RECORD
