Metadata-Version: 2.1
Name: odoo14-addon-ssi-hr-recruitment
Version: 14.0.1.0.1.dev1
Summary: HR - Recruitment
Home-page: https://simetri-sinergi.id
Author: OpenSynergy Indonesia, PT. Simetri Sinergi Indonesia
License: AGPL-3
Platform: UNKNOWN
Classifier: Programming Language :: Python
Classifier: Framework :: Odoo
Classifier: Framework :: Odoo :: 14.0
Classifier: License :: OSI Approved :: GNU Affero General Public License v3
Requires-Python: >=3.6
Requires-Dist: odoo14-addon-ssi-duration-mixin
Requires-Dist: odoo14-addon-ssi-hr-employee
Requires-Dist: odoo14-addon-ssi-hr-employee-experience-from-work-address
Requires-Dist: odoo14-addon-ssi-hr-employee-identification-from-work-address
Requires-Dist: odoo14-addon-ssi-hr-employee-language-from-work-address
Requires-Dist: odoo14-addon-ssi-hr-employee-personal-from-work-address
Requires-Dist: odoo14-addon-ssi-master-data-mixin
Requires-Dist: odoo14-addon-ssi-state-change-history-mixin
Requires-Dist: odoo14-addon-ssi-transaction-cancel-mixin
Requires-Dist: odoo14-addon-ssi-transaction-confirm-mixin
Requires-Dist: odoo14-addon-ssi-transaction-done-mixin
Requires-Dist: odoo14-addon-ssi-transaction-open-mixin
Requires-Dist: odoo14-addon-ssi-transaction-terminate-mixin
Requires-Dist: odoo <14.1dev,>=14.0a
